[
   {
      "salt" : "dmlTFbwPy7X2k2xqIWhVAw==",
      "accounts" : [
         {
            "password" : "N2jN6U+79pE/mjlkzy0gX6gRWQ==",
            "iv" : "cLmi8Dl68E2RBg1Cp2JCQA==",
            "url" : "okay",
            "username" : "hi"
         },
         {
            "password" : "VPHJLM0U+59c0PUCcqzm1mYMbzUWjVg=",
            "iv" : "DimLxM+Bn1O8b1L2z01MTQ==",
            "url" : "okay.com",
            "username" : "me"
         },
         {
            "password" : "pTm09Zcv14fZWsUPr8F+N+qX",
            "iv" : "9LFVf9MPNhFMq2btHNJevQ==",
            "url" : "gogole",
            "username" : "hu"
         },
         {
            "password" : "DyU7lamZdWQx1VYrW38OzYr2",
            "iv" : "gYCHTxxz5+VtEVlf8YJXig==",
            "url" : "goo",
            "username" : "hy"
         },
         {
            "password" : "qiUdkRSNzd8BdjsHVKBtZMQY67Q=",
            "iv" : "OmDw/JZ0PZBOjnnJitHYww==",
            "url" : "json",
            "username" : "ok"
         },
         {
            "password" : "YPL8hsZ6Qzhz0QcmqAnQcfw=",
            "iv" : "AEYRxgzR40fpLQx0G115eA==",
            "url" : "t",
            "username" : "t"
         },
         {
            "password" : "a93pu4/Z/ED6urWNoAfH5tY=",
            "iv" : "8FweWP+VHtlNQX4gsdnf9Q==",
            "url" : "j",
            "username" : "h"
         },
         {
            "password" : "l6iFAjyEDvcNRguVGrpeyLE=",
            "iv" : "5tYIV4MYmPerkDvsUsQXLQ==",
            "url" : "k",
            "username" : "k"
         },
         {
            "password" : "RBUaM/oDdMRuzwfRVsIUgEJASA==",
            "iv" : "FDLSHc+j9y9xuC8S9TikAQ==",
            "url" : "ok",
            "username" : "hi"
         }
      ]
   }
]
